rtl/uart_tx.v
module uart_tx (

    input clk,
    input reset,
    input baud_tick,

    input [7:0] data_in,
    input data_valid,

    output reg tx,
    output reg tx_done
);

parameter IDLE  = 2'b00;
parameter START = 2'b01;
parameter DATA  = 2'b10;
parameter STOP  = 2'b11;

reg [1:0] state;
reg [7:0] shift_reg;
reg [2:0] bit_index;

always @(posedge clk or posedge reset)
begin

    if (reset)
    begin
        state <= IDLE;

        tx <= 1'b1;
        tx_done <= 0;

        shift_reg <= 0;
        bit_index <= 0;
    end

    else
    begin

        tx_done <= 0;

        if (baud_tick)
        begin

            case(state)

                IDLE:
                begin
                    tx <= 1'b1;

                    if (data_valid)
                    begin
                        shift_reg <= data_in;
                        bit_index <= 0;
                        state <= START;
                    end
                end

                START:
                begin
                    tx <= 1'b0;
                    state <= DATA;
                end

                DATA:
                begin

                    tx <= shift_reg[0];

                    shift_reg <= shift_reg >> 1;

                    if (bit_index == 7)
                        state <= STOP;
                    else
                        bit_index <= bit_index + 1;

                end

                STOP:
                begin
                    tx <= 1'b1;
                    tx_done <= 1'b1;
                    state <= IDLE;
                end

            endcase

        end

    end

end

endmodule

tb/tb_uart_tx.v
`timescale 1ns/1ps

module tb_uart_tx;

reg clk;
reg reset;

reg baud_tick;

reg [7:0] data_in;
reg data_valid;

wire tx;
wire tx_done;

uart_tx uut (
    .clk(clk),
    .reset(reset),
    .baud_tick(baud_tick),
    .data_in(data_in),
    .data_valid(data_valid),
    .tx(tx),
    .tx_done(tx_done)
);

initial
begin
    clk = 0;
    forever #10 clk = ~clk;
end

initial
begin

    $dumpfile("tx_dump.vcd");
    $dumpvars(0, tb_uart_tx);

    reset = 1;
    baud_tick = 0;

    data_in = 8'b10101010;
    data_valid = 0;

    #100;
    reset = 0;

    #50;

    data_valid = 1;

    #20;
    data_valid = 0;

    repeat(12)
    begin
        #100;
        baud_tick = 1;

        #20;
        baud_tick = 0;
    end

    #500;

    $finish;

end

endmodule

tx_dump.vcd
$date
	Sat May  9 17:21:54 2026
$end
$version
	Icarus Verilog
$end
$timescale
	1ps
$end
$scope module tb_uart_tx $end
$var wire 1 ! tx_done $end
$var wire 1 " tx $end
$var reg 1 # baud_tick $end
$var reg 1 $ clk $end
$var reg 8 % data_in [7:0] $end
$var reg 1 & data_valid $end
$var reg 1 ' reset $end
$scope module uut $end
$var wire 1 # baud_tick $end
$var wire 1 $ clk $end
$var wire 8 ( data_in [7:0] $end
$var wire 1 & data_valid $end
$var wire 1 ' reset $end
$var parameter 2 ) DATA $end
$var parameter 2 * IDLE $end
$var parameter 2 + START $end
$var parameter 2 , STOP $end
$var reg 3 - bit_index [2:0] $end
$var reg 8 . shift_reg [7:0] $end
$var reg 2 / state [1:0] $end
$var reg 1 " tx $end
$var reg 1 ! tx_done $end
$upscope $end
$upscope $end
$enddefinitions $end
$comment Show the parameter values. $end
$dumpall
b11 ,
b1 +
b0 *
b10 )
$end
#0
$dumpvars
b0 /
b0 .
b0 -
b10101010 (
1'
0&
b10101010 %
0$
0#
1"
0!
$end
#10000
1$
#20000
0$
#30000
1$
#40000
0$
#50000
1$
#60000
0$
#70000
1$
#80000
0$
#90000
1$
#100000
0$
0'
#110000
1$
#120000
0$
#130000
1$
#140000
0$
#150000
1$
1&
#160000
0$
#170000
1$
0&
#180000
0$
#190000
1$
#200000
0$
#210000
1$
#220000
0$
#230000
1$
#240000
0$
#250000
1$
#260000
0$
#270000
1$
1#
#280000
0$
#290000
1$
0#
#300000
0$
#310000
1$
#320000
0$
#330000
1$
#340000
0$
#350000
1$
#360000
0$
#370000
1$
#380000
0$
#390000
1$
1#
#400000
0$
#410000
1$
0#
#420000
0$
#430000
1$
#440000
0$
#450000
1$
#460000
0$
#470000
1$
#480000
0$
#490000
1$
#500000
0$
#510000
1$
1#
#520000
0$
#530000
1$
0#
#540000
0$
#550000
1$
#560000
0$
#570000
1$
#580000
0$
#590000
1$
#600000
0$
#610000
1$
#620000
0$
#630000
1$
1#
#640000
0$
#650000
1$
0#
#660000
0$
#670000
1$
#680000
0$
#690000
1$
#700000
0$
#710000
1$
#720000
0$
#730000
1$
#740000
0$
#750000
1$
1#
#760000
0$
#770000
1$
0#
#780000
0$
#790000
1$
#800000
0$
#810000
1$
#820000
0$
#830000
1$
#840000
0$
#850000
1$
#860000
0$
#870000
1$
1#
#880000
0$
#890000
1$
0#
#900000
0$
#910000
1$
#920000
0$
#930000
1$
#940000
0$
#950000
1$
#960000
0$
#970000
1$
#980000
0$
#990000
1$
1#
#1000000
0$
#1010000
1$
0#
#1020000
0$
#1030000
1$
#1040000
0$
#1050000
1$
#1060000
0$
#1070000
1$
#1080000
0$
#1090000
1$
#1100000
0$
#1110000
1$
1#
#1120000
0$
#1130000
1$
0#
#1140000
0$
#1150000
1$
#1160000
0$
#1170000
1$
#1180000
0$
#1190000
1$
#1200000
0$
#1210000
1$
#1220000
0$
#1230000
1$
1#
#1240000
0$
#1250000
1$
0#
#1260000
0$
#1270000
1$
#1280000
0$
#1290000
1$
#1300000
0$
#1310000
1$
#1320000
0$
#1330000
1$
#1340000
0$
#1350000
1$
1#
#1360000
0$
#1370000
1$
0#
#1380000
0$
#1390000
1$
#1400000
0$
#1410000
1$
#1420000
0$
#1430000
1$
#1440000
0$
#1450000
1$
#1460000
0$
#1470000
1$
1#
#1480000
0$
#1490000
1$
0#
#1500000
0$
#1510000
1$
#1520000
0$
#1530000
1$
#1540000
0$
#1550000
1$
#1560000
0$
#1570000
1$
#1580000
0$
#1590000
1$
1#
#1600000
0$
#1610000
1$
0#
